Metadata-Version: 2.1
Name: testout
Version: 0.0.3
Summary: testout
Home-page: https://gitee.com/AlwaysLee/cgf-ml_sdk-python.git
Author: cgf
Author-email: 512070806@qq.com
License: MIT
Platform: UNKNOWN
